{
	"poki_template_version": 1,
	"extra_html": {
	  "head": [
		"<!-- will be copied to the resulting head //-->"
	  ],
	  "body": [
		"<!-- will be copied to the resulting body //-->",
		"<!-- will also be copied to the resulting body //-->"
	  ]
	},
	"background_color": "#231F20",
	"background_filename": "",
	"code_filename": "6a3cdc2fd379fa3fef7d9756fcd27f78.wasm",
	"company_name": "SMJ",
	"data_filename": "42a74f16dbe8d84565a6aa9284ef5351.data",
	"decompression_fallback": "Disabled",
	"development_player": "false",
	"framework_filename": "9f16bf2cbbc643d6c3e6dea1eb7e25ae.framework.js",
	"height": "600",
	"loader_filename": "7bf34013a7f7da6a58f8da3519c97c81.loader.js",
	"memory_filename": "",
	"product_name": "BoxEm",
	"product_version": "0.0.56",
	"splash_screen_style": "Dark",
	"symbols_filename": "",
	"unity_version": "2022.3.32f1",
	"use_data_caching": "true",
	"use_threads": "false",
	"use_wasm": "true",
	"use_webgl_1_0": "true",
	"use_webgl_2_0": "true",
	"width": "960"
  }
